keras_vggface/__init__.py
keras_vggface/models.py
keras_vggface/utils.py
keras_vggface/version.py
keras_vggface/vggface.py
keras_vggface-0.6.dist-info/LICENSE.txt
keras_vggface-0.6.dist-info/METADATA
keras_vggface-0.6.dist-info/WHEEL
keras_vggface-0.6.dist-info/top_level.txt
keras_vggface-0.6.dist-info/RECORD
